{
  "project_info": {
    "project_number": "309939260161",
    "project_id": "howistagram-f16-9d34d",
    "storage_bucket": "howistagram-f16-9d34d.appspot.com"
  },
  "client": [
    {
      "client_info": {
        "mobilesdk_app_id": "1:309939260161:android:ebfaa07cb1a914a10d6900",
        "android_client_info": {
          "package_name": "com.example.howistagram_f16"
        }
      },
      "oauth_client": [
        {
          "client_id": "309939260161-nrn51okh9slij0cbifcbveqkjun0rcpn.apps.googleusercontent.com",
          "client_type": 3
        }
      ],
      "api_key": [
        {
          "current_key": "AIzaSyDys4AOaAABroFRU4H-PEObPWAFm5S_CUg"
        }
      ],
      "services": {
        "appinvite_service": {
          "other_platform_oauth_client": [
            {
              "client_id": "309939260161-nrn51okh9slij0cbifcbveqkjun0rcpn.apps.googleusercontent.com",
              "client_type": 3
            }
          ]
        }
      }
    }
  ],
  "configuration_version": "1"
}